copy_cat/__init__.py
copy_cat/copy_cat.py
ryans_copycat-0.0.1.dist-info/LICENSE
ryans_copycat-0.0.1.dist-info/METADATA
ryans_copycat-0.0.1.dist-info/WHEEL
ryans_copycat-0.0.1.dist-info/top_level.txt
ryans_copycat-0.0.1.dist-info/RECORD
