Metadata-Version: 2.1
Name: ryans-copycat
Version: 0.0.1
Summary: Ryan's Copy Cat
Author: Ryan Li
Author-email: <mail@go.com>
Keywords: copy,cat
Classifier: Development Status :: 1 - Planning
Classifier: Intended Audience :: Developers
Classifier: Programming Language :: Python :: 3
Classifier: Operating System :: Unix
Classifier: Operating System :: MacOS :: MacOS X
Classifier: Operating System :: Microsoft :: Windows
Requires-Python: >=3.9
License-File: LICENSE
Provides-Extra: dev
Requires-Dist: twine >=4.0.2 ; extra == 'dev'
